{
    "Cores[1]": [
        1.0,
        1.0,
        1.0,
        1.0,
        1.0,
        1.0,
        1.0,
        1.0,
        1.0,
        1.0,
        1.0,
        1.0,
        1.81,
        1.81,
        1.81,
        2.78,
        2.78,
        2.78,
        3.67,
        3.67,
        3.67,
        1.93,
        1.93,
        1.93,
        1.0,
        1.0,
        1.0,
        1.6,
        1.6,
        1.6
    ],
    "Cores[2]": [
        1.0,
        1.0,
        1.0,
        1.0,
        1.0,
        1.0,
        1.0,
        1.0,
        1.0,
        1.0,
        1.0,
        1.0,
        1.64,
        1.64,
        1.64,
        2.84,
        2.84,
        2.84,
        3.25,
        3.25,
        3.25,
        1.86,
        1.86,
        1.86,
        1.0,
        1.0,
        1.0,
        1.58,
        1.58,
        1.58
    ],
    "Cores[3]": [
        1.0,
        1.0,
        1.0,
        1.0,
        1.0,
        1.0,
        1.0,
        1.0,
        1.0,
        1.0,
        1.0,
        1.0,
        1.18,
        1.18,
        1.18,
        2.06,
        2.06,
        2.06,
        2.53,
        2.53,
        2.53,
        1.43,
        1.43,
        1.43,
        1.0,
        1.0,
        1.0,
        1.14,
        1.14,
        1.14
    ],
    "Cores[4]": [
        1.0,
        1.0,
        1.0,
        1.0,
        1.0,
        1.0,
        1.0,
        1.0,
        1.0,
        1.0,
        1.0,
        1.0,
        1.58,
        1.58,
        1.58,
        2.63,
        2.63,
        2.63,
        3.16,
        3.16,
        3.16,
        1.76,
        1.76,
        1.76,
        1.0,
        1.0,
        1.0,
        1.49,
        1.49,
        1.49
    ],
    "Cores[5]": [
        1.0,
        1.0,
        1.0,
        1.0,
        1.0,
        1.0,
        1.0,
        1.0,
        1.0,
        1.0,
        1.0,
        1.0,
        1.0,
        1.0,
        1.0,
        1.5,
        1.5,
        1.5,
        1.92,
        1.92,
        1.92,
        1.11,
        1.11,
        1.11,
        1.0,
        1.0,
        1.0,
        1.0,
        1.0,
        1.0
    ],
    "Cores[6]": [
        1.0,
        1.0,
        1.0,
        1.0,
        1.0,
        1.0,
        1.0,
        1.0,
        1.0,
        1.0,
        1.0,
        1.0,
        1.36,
        1.36,
        1.36,
        2.27,
        2.27,
        2.27,
        2.73,
        2.73,
        2.73,
        1.52,
        1.52,
        1.52,
        1.0,
        1.0,
        1.0,
        1.29,
        1.29,
        1.29
    ],
    "Cores[7]": [
        1.0,
        1.0,
        1.0,
        1.0,
        1.0,
        1.0,
        1.0,
        1.0,
        1.0,
        1.0,
        1.0,
        1.0,
        1.94,
        1.94,
        1.94,
        3.46,
        3.46,
        3.46,
        4.0,
        4.0,
        4.0,
        2.3,
        2.3,
        2.3,
        1.0,
        1.0,
        1.0,
        2.0,
        2.0,
        2.0
    ],
    "Cores[8]": [
        1.0,
        1.0,
        1.0,
        1.0,
        1.0,
        1.0,
        1.0,
        1.0,
        1.0,
        1.0,
        1.0,
        1.0,
        1.0,
        1.0,
        1.0,
        1.41,
        1.41,
        1.41,
        1.85,
        1.85,
        1.85,
        1.0,
        1.0,
        1.0,
        1.0,
        1.0,
        1.0,
        1.0,
        1.0,
        1.0
    ],
    "Cores[9]": [
        1.0,
        1.0,
        1.0,
        1.0,
        1.0,
        1.0,
        1.0,
        1.0,
        1.0,
        1.0,
        1.0,
        1.0,
        1.51,
        1.51,
        1.51,
        2.63,
        2.63,
        2.63,
        2.94,
        2.94,
        2.94,
        1.68,
        1.68,
        1.68,
        1.0,
        1.0,
        1.0,
        1.43,
        1.43,
        1.43
    ]
}